setup.py
django_render.egg-info/PKG-INFO
django_render.egg-info/SOURCES.txt
django_render.egg-info/dependency_links.txt
django_render.egg-info/requires.txt
django_render.egg-info/top_level.txt
render/__init__.py
render/mixins.py