Metadata-Version: 1.1
Name: django-render
Version: 0.3.7
Summary: Django templates rendering sugar
Home-page: https://github.com/phpdude/django-render
Author: Alexandr I. Shurigin
Author-email: ya@helldude.ru
License: UNKNOWN
Platform: UNKNOWN
Classifier: Framework :: Django
Classifier: Operating System :: OS Independent
Classifier: Topic :: Software Development
